fingafrog/__init__.py
fingafrog/main.py
fingafrog-0.0.0.dist-info/METADATA
fingafrog-0.0.0.dist-info/WHEEL
fingafrog-0.0.0.dist-info/entry_points.txt
fingafrog-0.0.0.dist-info/top_level.txt
fingafrog-0.0.0.dist-info/RECORD
