Metadata-Version: 2.1
Name: fingafrog
Version: 0.0.0
Summary: A fingafrog python package.
Home-page: https://github.com/fingafrog/fingafrog
Author: Chris Pryer
Author-email: christophpryer@gmail.com
License: PUBLIC
Platform: UNKNOWN
